apirouter/__init__.py
apirouter/conf.py
apirouter/decorators.py
apirouter/exception_handler.py
apirouter/exceptions.py
apirouter/request.py
apirouter/response.py
apirouter/routing.py
apirouter/types.py
apirouter/utils.py
django_apirouter-0.2.1.dist-info/LICENSE
django_apirouter-0.2.1.dist-info/WHEEL
django_apirouter-0.2.1.dist-info/METADATA
django_apirouter-0.2.1.dist-info/RECORD
