Metadata-Version: 2.1
Name: django-apirouter
Version: 0.2.1
Summary: Django API router
Home-page: https://github.com/antonrh/django-apirouter
License: MIT
Keywords: django,api,rest
Author: Anton Ruhlov
Author-email: antonruhlov@gmail.com
Requires-Python: >=3.6,<4.0
Classifier: License :: OSI Approved :: MIT License
Classifier: Programming Language :: Python :: 3
Classifier: Programming Language :: Python :: 3.6
Classifier: Programming Language :: Python :: 3.7
Classifier: Programming Language :: Python :: 3.8
Requires-Dist: attrs (>=19.3.0,<20.0.0)
Requires-Dist: django (>=3.0.8,<4.0.0)
Requires-Dist: mkdocs-material[docs] (>=5.5.0,<6.0.0)
Requires-Dist: mkdocs[docs] (>=1.1.2,<2.0.0)
Requires-Dist: mkdocstrings[docs] (>=0.12.2,<0.13.0)
Project-URL: Repository, https://github.com/antonrh/django-apirouter
